easy_entrez/__init__.py
easy_entrez/api.py
easy_entrez/batch.py
easy_entrez/data.py
easy_entrez/parsing.py
easy_entrez/py.typed
easy_entrez/queries.py
easy_entrez/types.py
easy_entrez/data/entrez_databases.tsv
easy_entrez-0.3.7.dist-info/LICENSE
easy_entrez-0.3.7.dist-info/METADATA
easy_entrez-0.3.7.dist-info/WHEEL
easy_entrez-0.3.7.dist-info/top_level.txt
easy_entrez-0.3.7.dist-info/RECORD
