Metadata-Version: 2.1
Name: easy-entrez
Version: 0.3.7
Summary: Python REST API for Entrez E-Utilities: stateless, easy to use, reliable.
Home-page: https://github.com/krassowski/easy-entrez
Author: Michal Krassowski
Author-email: krassowski.michal+pypi@gmail.com
License: MIT
Keywords: entrez,pubmed,e-utilities,ncbi,rest,api,dbsnp,literature,mining
Classifier: Development Status :: 5 - Production/Stable
Classifier: License :: OSI Approved :: GNU Lesser General Public License v3 (LGPLv3)
Classifier: Operating System :: Microsoft :: Windows
Classifier: Operating System :: POSIX :: Linux
Classifier: Operating System :: MacOS
Classifier: Topic :: Utilities
Classifier: Topic :: Database
Classifier: Topic :: Scientific/Engineering :: Bio-Informatics
Classifier: Topic :: Software Development :: Libraries :: Python Modules
Classifier: Typing :: Typed
Classifier: Intended Audience :: Developers
Classifier: Intended Audience :: Science/Research
Classifier: Programming Language :: Python :: 3.7
Classifier: Programming Language :: Python :: 3.8
Classifier: Programming Language :: Python :: 3.9
Classifier: Programming Language :: Python :: 3.10
Classifier: Programming Language :: Python :: 3.11
License-File: LICENSE
Requires-Dist: requests
Requires-Dist: typing-extensions
Provides-Extra: docs
Requires-Dist: sphinx <6.0 ; extra == 'docs'
Requires-Dist: pydata-sphinx-theme ; extra == 'docs'
Requires-Dist: sphinx-autodoc-typehints ; extra == 'docs'
Requires-Dist: sphinx-copybutton ; extra == 'docs'
Requires-Dist: myst-parser ; extra == 'docs'
Provides-Extra: with_parsing_utils
Requires-Dist: pandas ; extra == 'with_parsing_utils'
Provides-Extra: with_progress_bars
Requires-Dist: tqdm ; extra == 'with_progress_bars'
